query_farm_flight_server/__init__.py
query_farm_flight_server/admin.py
query_farm_flight_server/auth.py
query_farm_flight_server/auth_manager.py
query_farm_flight_server/auth_manager_dynamodb.py
query_farm_flight_server/auth_manager_memory.py
query_farm_flight_server/auth_manager_naive.py
query_farm_flight_server/exceptions.py
query_farm_flight_server/flight_handling.py
query_farm_flight_server/flight_inventory.py
query_farm_flight_server/middleware.py
query_farm_flight_server/parameter_types.py
query_farm_flight_server/py.typed
query_farm_flight_server/schema_uploader.py
query_farm_flight_server/server.py
query_farm_flight_server/test_action_decoders.py
query_farm_flight_server/test_action_decorators.py
query_farm_flight_server/test_auth_manager_dynamodb.py
query_farm_flight_server/test_auth_manager_memory.py
query_farm_flight_server/test_auth_manager_naive.py
query_farm_flight_server/util.py
query_farm_flight_server-0.1.17.dist-info/METADATA
query_farm_flight_server-0.1.17.dist-info/WHEEL
query_farm_flight_server-0.1.17.dist-info/licenses/LICENSE
query_farm_flight_server-0.1.17.dist-info/RECORD
