Metadata-Version: 2.3
Name: query-farm-flight-server
Version: 0.1.17
Summary: A framework for building Arrow Flight servers for the DuckDB Airport extension with robust authentication, schema management, and data handling capabilities.
Project-URL: Repository, https://github.com/query-farm/python-flight-server.git
Project-URL: Issues, https://github.com/query-farm/python-flight-server/issues
Author-email: Rusty Conover <hello@query.farm>
Keywords: airport,arrow,arrow flight,duckdb,duckdb airport,flight,predicate pushdown,predicates,sql,sql parsing
Classifier: Development Status :: 4 - Beta
Classifier: Intended Audience :: Developers
Classifier: Programming Language :: Python :: 3.12
Classifier: Topic :: Database
Classifier: Topic :: Database :: Database Engines/Servers
Requires-Python: >=3.12
Requires-Dist: boto3>=1.35.0
Requires-Dist: cache3>=0.4.3
Requires-Dist: click>=8.1.7
Requires-Dist: fuzzywuzzy>=0.18.0
Requires-Dist: msgpack>=1.1.0
Requires-Dist: mypy-boto3-dynamodb>=1.35.24
Requires-Dist: mypy-boto3-s3>=1.35.42
Requires-Dist: prettytable>=3.11.0
Requires-Dist: pyarrow>=19.0.0
Requires-Dist: pydantic>=2.9.2
Requires-Dist: python-levenshtein>=0.26.0
Requires-Dist: sentry-sdk>=2.16.0
Requires-Dist: structlog>=24.4.0
Requires-Dist: zstandard>=0.23.0
